[{
  "_id": {
    "$oid": "67523ea76f73c43ba4eb3482"
  },
  "rescue_date": {
    "$date": "2024-05-03T03:00:00.000Z"
  },
  "case_number": "1",
  "critter_count": 3,
  "rescue_role": "Relay",
  "animal_type": "Star-nose Mole",
  "animal_age": "Baby",
  "conservation_status": "Least Concern",
  "original_location": "Yarmouth",
  "volunteer_notes": "",
  "km_driven": 182,
  "user": {
    "$oid": "6755ed21907200876877bf8a"
  }
},
{
  "_id": {
    "$oid": "67523ea76f73c43ba4eb3483"
  },
  "rescue_date": {
    "$date": "2024-05-10T03:00:00.000Z"
  },
  "case_number": "2",
  "critter_count": 1,
  "rescue_role": "Relay",
  "animal_type": "Herring Gull",
  "animal_age": "Adult",
  "conservation_status": "Least Concern",
  "original_location": "Yarmouth",
  "volunteer_notes": "",
  "km_driven": 182,
  "user": {
    "$oid": "6755ed21907200876877bf8a"
  }
},
{
  "_id": {
    "$oid": "67523ea76f73c43ba4eb3484"
  },
  "rescue_date": {
    "$date": "2024-05-15T03:00:00.000Z"
  },
  "case_number": "3",
  "critter_count": 1,
  "rescue_role": "Pickup",
  "animal_type": "Dark-eyed Junco",
  "animal_age": "Adult",
  "conservation_status": "Least Concern",
  "original_location": "Barrington",
  "volunteer_notes": "",
  "km_driven": 245,
  "user": {
    "$oid": "6755ed21907200876877bf8a"
  }
},
{
  "_id": {
    "$oid": "67523ea76f73c43ba4eb3485"
  },
  "rescue_date": {
    "$date": "2024-05-24T03:00:00.000Z"
  },
  "case_number": "4",
  "critter_count": 1,
  "rescue_role": "Pickup",
  "animal_type": "Fox",
  "animal_age": "Baby",
  "conservation_status": "Least Concern",
  "original_location": "Sable River",
  "volunteer_notes": "",
  "km_driven": 145,
  "user": {
    "$oid": "6755ed21907200876877bf8a"
  }
},
{
  "_id": {
    "$oid": "67523ea76f73c43ba4eb3486"
  },
  "rescue_date": {
    "$date": "2024-06-09T03:00:00.000Z"
  },
  "case_number": "5",
  "critter_count": 1,
  "rescue_role": "Pickup",
  "animal_type": "Red-eyed Vireo",
  "animal_age": "Adult",
  "conservation_status": "Least Concern",
  "original_location": "Bridgewater",
  "volunteer_notes": "",
  "km_driven": 96,
  "user": {
    "$oid": "6755ed21907200876877bf8a"
  }
},
{
  "_id": {
    "$oid": "67523ea76f73c43ba4eb3487"
  },
  "rescue_date": {
    "$date": "2024-06-10T03:00:00.000Z"
  },
  "case_number": "6",
  "critter_count": 1,
  "rescue_role": "Pickup",
  "animal_type": "Barn Swallow",
  "animal_age": "Adult",
  "conservation_status": "Special Concern",
  "original_location": "Keji",
  "volunteer_notes": "",
  "km_driven": 139,
  "user": {
    "$oid": "6755ed21907200876877bf8a"
  }
},
{
  "_id": {
    "$oid": "67523ea76f73c43ba4eb3488"
  },
  "rescue_date": {
    "$date": "2024-06-15T03:00:00.000Z"
  },
  "case_number": "7",
  "critter_count": 1,
  "rescue_role": "Capture",
  "animal_type": "Snapper",
  "animal_age": "Adult",
  "conservation_status": "Special Concern",
  "original_location": "Liverpool hwy",
  "volunteer_notes": "",
  "km_driven": 72,
  "user": {
    "$oid": "6755ed21907200876877bf8a"
  }
},
{
  "_id": {
    "$oid": "67523ea76f73c43ba4eb3489"
  },
  "rescue_date": {
    "$date": "2024-06-17T03:00:00.000Z"
  },
  "case_number": "8",
  "critter_count": 1,
  "rescue_role": "Pickup",
  "animal_type": "Black Scoter",
  "animal_age": "Baby",
  "conservation_status": "Special Concern",
  "original_location": "Clark's Harbour",
  "volunteer_notes": "Also drove to get live trap for baby raccons that weren't captured until next day.",
  "km_driven": 302,
  "user": {
    "$oid": "6755ed21907200876877bf8a"
  }
},
{
  "_id": {
    "$oid": "67523ea76f73c43ba4eb348a"
  },
  "rescue_date": {
    "$date": "2024-06-20T03:00:00.000Z"
  },
  "case_number": "9",
  "critter_count": 3,
  "rescue_role": "Pickup",
  "animal_type": "Barn Swallow",
  "animal_age": "Baby",
  "conservation_status": "Special Concern",
  "original_location": "New Albany",
  "volunteer_notes": "",
  "km_driven": 176,
  "user": {
    "$oid": "6755ed21907200876877bf8a"
  }
},
{
  "_id": {
    "$oid": "67523ea76f73c43ba4eb348b"
  },
  "rescue_date": {
    "$date": "2024-06-24T03:00:00.000Z"
  },
  "case_number": "10",
  "critter_count": 3,
  "rescue_role": "Relay",
  "animal_type": "Raccoon",
  "animal_age": "Baby",
  "conservation_status": "Least Concern",
  "original_location": "Yarmouth",
  "volunteer_notes": "",
  "km_driven": 182,
  "user": {
    "$oid": "6755ed21907200876877bf8a"
  }
},
{
  "_id": {
    "$oid": "67523ea76f73c43ba4eb348c"
  },
  "rescue_date": {
    "$date": "2024-06-25T03:00:00.000Z"
  },
  "case_number": "11",
  "critter_count": 1,
  "rescue_role": "Relay",
  "animal_type": "Unknown Gull",
  "animal_age": "Baby",
  "conservation_status": "Least Concern",
  "original_location": "Yarmouth",
  "volunteer_notes": "",
  "km_driven": 182,
  "user": {
    "$oid": "6755ed21907200876877bf8a"
  }
},
{
  "_id": {
    "$oid": "67523ea76f73c43ba4eb348d"
  },
  "rescue_date": {
    "$date": "2024-06-25T03:00:00.000Z"
  },
  "case_number": "12",
  "critter_count": 1,
  "rescue_role": "Pickup",
  "animal_type": "Black duck",
  "animal_age": "Juvenile",
  "conservation_status": "Least Concern",
  "original_location": "Liverpool",
  "volunteer_notes": "Drove from Middlewood",
  "km_driven": 56,
  "user": {
    "$oid": "6755ed21907200876877bf8a"
  }
},
{
  "_id": {
    "$oid": "67523ea76f73c43ba4eb348e"
  },
  "rescue_date": {
    "$date": "2024-06-25T03:00:00.000Z"
  },
  "case_number": "13",
  "critter_count": 1,
  "rescue_role": "Pickup",
  "animal_type": "Snapper",
  "animal_age": "Juvenile",
  "conservation_status": "Special Concern",
  "original_location": "Lockeport",
  "volunteer_notes": "Caller met me in Liverpool, Same trip as duck",
  "km_driven": 1,
  "user": {
    "$oid": "6755ed21907200876877bf8a"
  }
},
{
  "_id": {
    "$oid": "67523ea76f73c43ba4eb348f"
  },
  "rescue_date": {
    "$date": "2024-06-26T03:00:00.000Z"
  },
  "case_number": "14",
  "critter_count": 1,
  "rescue_role": "Pickup",
  "animal_type": "Common Grackle",
  "animal_age": "Adult",
  "conservation_status": "Least Concern",
  "original_location": "Shelburne",
  "volunteer_notes": "",
  "km_driven": 183,
  "user": {
    "$oid": "6755ed21907200876877bf8a"
  }
},
{
  "_id": {
    "$oid": "67523ea76f73c43ba4eb3490"
  },
  "rescue_date": {
    "$date": "2024-06-27T03:00:00.000Z"
  },
  "case_number": "15",
  "critter_count": 1,
  "rescue_role": "Relay",
  "animal_type": "European starling",
  "animal_age": "Baby",
  "conservation_status": "Invasive species",
  "original_location": "Yarmouth",
  "volunteer_notes": "",
  "km_driven": 182,
  "user": {
    "$oid": "6755ed21907200876877bf8a"
  }
},
{
  "_id": {
    "$oid": "67523ea76f73c43ba4eb3491"
  },
  "rescue_date": {
    "$date": "2024-06-27T03:00:00.000Z"
  },
  "case_number": "16",
  "critter_count": 1,
  "rescue_role": "Pickup",
  "animal_type": "Raccoon",
  "animal_age": "Baby",
  "conservation_status": "Least Concern",
  "original_location": "Shelburne",
  "volunteer_notes": "Same trip as starling",
  "km_driven": 1,
  "user": {
    "$oid": "6755ed21907200876877bf8a"
  }
},
{
  "_id": {
    "$oid": "67523ea76f73c43ba4eb3492"
  },
  "rescue_date": {
    "$date": "2024-06-29T03:00:00.000Z"
  },
  "case_number": "17",
  "critter_count": 1,
  "rescue_role": "Relay",
  "animal_type": "Raccoon",
  "animal_age": "Baby",
  "conservation_status": "Least Concern",
  "original_location": "Yarmouth",
  "volunteer_notes": "",
  "km_driven": 182,
  "user": {
    "$oid": "6755ed21907200876877bf8a"
  }
},
{
  "_id": {
    "$oid": "67523ea76f73c43ba4eb3493"
  },
  "rescue_date": {
    "$date": "2024-06-29T03:00:00.000Z"
  },
  "case_number": "18",
  "critter_count": 1,
  "rescue_role": "Pickup",
  "animal_type": "Herring Gull",
  "animal_age": "Adult",
  "conservation_status": "Least Concern",
  "original_location": "Barrington",
  "volunteer_notes": "Caller met me in Jordan Falls",
  "km_driven": 166,
  "user": {
    "$oid": "6755ed21907200876877bf8a"
  }
},
{
  "_id": {
    "$oid": "67523ea76f73c43ba4eb3494"
  },
  "rescue_date": {
    "$date": "2024-06-30T03:00:00.000Z"
  },
  "case_number": "19",
  "critter_count": 1,
  "rescue_role": "Pickup",
  "animal_type": "Herring Gull",
  "animal_age": "Adult",
  "conservation_status": "Least Concern",
  "original_location": "Yarmouth",
  "volunteer_notes": "Caller met me in Shelburne",
  "km_driven": 133,
  "user": {
    "$oid": "6755ed21907200876877bf8a"
  }
},
{
  "_id": {
    "$oid": "67523ea76f73c43ba4eb3495"
  },
  "rescue_date": {
    "$date": "2024-07-02T03:00:00.000Z"
  },
  "case_number": "20",
  "critter_count": 1,
  "rescue_role": "Pickup",
  "animal_type": "Northern Flicker",
  "animal_age": "Adult",
  "conservation_status": "Least Concern",
  "original_location": "Nineveh",
  "volunteer_notes": "",
  "km_driven": 146,
  "user": {
    "$oid": "6755ed21907200876877bf8a"
  }
},
{
  "_id": {
    "$oid": "67523ea76f73c43ba4eb3496"
  },
  "rescue_date": {
    "$date": "2024-07-03T03:00:00.000Z"
  },
  "case_number": "21",
  "critter_count": 1,
  "rescue_role": "Relay",
  "animal_type": "Skunk",
  "animal_age": "Baby",
  "conservation_status": "Least Concern",
  "original_location": "Port Maitland",
  "volunteer_notes": "",
  "km_driven": 182,
  "user": {
    "$oid": "6755ed21907200876877bf8a"
  }
},
{
  "_id": {
    "$oid": "67523ea76f73c43ba4eb3497"
  },
  "rescue_date": {
    "$date": "2024-07-04T03:00:00.000Z"
  },
  "case_number": "22",
  "critter_count": 1,
  "rescue_role": "Relay",
  "animal_type": "Herring Gull",
  "animal_age": "Juvenile",
  "conservation_status": "Least Concern",
  "original_location": "Yarmouth",
  "volunteer_notes": "",
  "km_driven": 186,
  "user": {
    "$oid": "6755ed21907200876877bf8a"
  }
},
{
  "_id": {
    "$oid": "67523ea76f73c43ba4eb3498"
  },
  "rescue_date": {
    "$date": "2024-07-05T03:00:00.000Z"
  },
  "case_number": "23",
  "critter_count": 1,
  "rescue_role": "Capture",
  "animal_type": "Raccoon",
  "animal_age": "Baby",
  "conservation_status": "Least Concern",
  "original_location": "Bridgewater",
  "volunteer_notes": "Side of rd next to dead sibling :(",
  "km_driven": 98,
  "user": {
    "$oid": "6755ed21907200876877bf8a"
  }
},
{
  "_id": {
    "$oid": "67523ea76f73c43ba4eb3499"
  },
  "rescue_date": {
    "$date": "2024-07-07T03:00:00.000Z"
  },
  "case_number": "24",
  "critter_count": 1,
  "rescue_role": "Pickup",
  "animal_type": "Canada Goose",
  "animal_age": "Juvenile",
  "conservation_status": "Least Concern",
  "original_location": "Lockeport",
  "volunteer_notes": "",
  "km_driven": 30,
  "user": {
    "$oid": "6755ed21907200876877bf8a"
  }
},
{
  "_id": {
    "$oid": "67523ea76f73c43ba4eb349a"
  },
  "rescue_date": {
    "$date": "2024-07-08T03:00:00.000Z"
  },
  "case_number": "25",
  "critter_count": 1,
  "rescue_role": "Pickup",
  "animal_type": "Northern Flicker",
  "animal_age": "Adult",
  "conservation_status": "Least Concern",
  "original_location": "Barrington",
  "volunteer_notes": "Caller met me in Shelburne",
  "km_driven": 182,
  "user": {
    "$oid": "6755ed21907200876877bf8a"
  }
},
{
  "_id": {
    "$oid": "67523ea76f73c43ba4eb349b"
  },
  "rescue_date": {
    "$date": "2024-07-12T03:00:00.000Z"
  },
  "case_number": "26",
  "critter_count": 1,
  "rescue_role": "Pickup",
  "animal_type": "Unknown Gull",
  "animal_age": "Baby",
  "conservation_status": "Least Concern",
  "original_location": "Yarmouth",
  "volunteer_notes": "",
  "km_driven": 251,
  "user": {
    "$oid": "6755ed21907200876877bf8a"
  }
},
{
  "_id": {
    "$oid": "67523ea76f73c43ba4eb349c"
  },
  "rescue_date": {
    "$date": "2024-07-14T03:00:00.000Z"
  },
  "case_number": "27",
  "critter_count": 1,
  "rescue_role": "Pickup",
  "animal_type": "Robin",
  "animal_age": "Juvenile",
  "conservation_status": "Least Concern",
  "original_location": "Port La Tour",
  "volunteer_notes": "Caller met me in Shelburne",
  "km_driven": 182,
  "user": {
    "$oid": "6755ed21907200876877bf8a"
  }
},
{
  "_id": {
    "$oid": "67523ea76f73c43ba4eb349d"
  },
  "rescue_date": {
    "$date": "2024-07-15T03:00:00.000Z"
  },
  "case_number": "28",
  "critter_count": 1,
  "rescue_role": "Relay",
  "animal_type": "Raccoon",
  "animal_age": "Juvenile",
  "conservation_status": "Least Concern",
  "original_location": "Tusket",
  "volunteer_notes": "",
  "km_driven": 182,
  "user": {
    "$oid": "6755ed21907200876877bf8a"
  }
},
{
  "_id": {
    "$oid": "67523ea76f73c43ba4eb349e"
  },
  "rescue_date": {
    "$date": "2024-07-15T03:00:00.000Z"
  },
  "case_number": "29",
  "critter_count": 1,
  "rescue_role": "Pickup",
  "animal_type": "Robin",
  "animal_age": "Juvenile",
  "conservation_status": "Least Concern",
  "original_location": "Caledonia",
  "volunteer_notes": "Caller met me in Liverpool, Same trip as raccoon",
  "km_driven": 1,
  "user": {
    "$oid": "6755ed21907200876877bf8a"
  }
},
{
  "_id": {
    "$oid": "67523ea76f73c43ba4eb349f"
  },
  "rescue_date": {
    "$date": "2024-07-23T03:00:00.000Z"
  },
  "case_number": "30",
  "critter_count": 1,
  "rescue_role": "Relay",
  "animal_type": "Broadwinged Hawk",
  "animal_age": "Baby",
  "conservation_status": "Least Concern",
  "original_location": "Tusket",
  "volunteer_notes": "",
  "km_driven": 182,
  "user": {
    "$oid": "6755ed21907200876877bf8a"
  }
},
{
  "_id": {
    "$oid": "67523ea76f73c43ba4eb34a0"
  },
  "rescue_date": {
    "$date": "2024-07-24T03:00:00.000Z"
  },
  "case_number": "31",
  "critter_count": 3,
  "rescue_role": "Relay",
  "animal_type": "Herring Gull",
  "animal_age": "Juvenile",
  "conservation_status": "Least Concern",
  "original_location": "Yarmouth",
  "volunteer_notes": "Volunteered at drop-off and drove from there for relay, also dropped off letters",
  "km_driven": 239,
  "user": {
    "$oid": "6755ed21907200876877bf8a"
  }
},
{
  "_id": {
    "$oid": "67523ea76f73c43ba4eb34a1"
  },
  "rescue_date": {
    "$date": "2024-07-25T03:00:00.000Z"
  },
  "case_number": "32",
  "critter_count": 1,
  "rescue_role": "Capture",
  "animal_type": "Porcupine",
  "animal_age": "Baby",
  "conservation_status": "Least Concern",
  "original_location": "Shelburne",
  "volunteer_notes": "So cute! First porcupine rescue ever",
  "km_driven": 185,
  "user": {
    "$oid": "6755ed21907200876877bf8a"
  }
},
{
  "_id": {
    "$oid": "67523ea76f73c43ba4eb34a2"
  },
  "rescue_date": {
    "$date": "2024-07-28T03:00:00.000Z"
  },
  "case_number": "33",
  "critter_count": 1,
  "rescue_role": "Relay",
  "animal_type": "Herring Gull",
  "animal_age": "Juvenile",
  "conservation_status": "Least Concern",
  "original_location": "Yarmouth",
  "volunteer_notes": "",
  "km_driven": 182,
  "user": {
    "$oid": "6755ed21907200876877bf8a"
  }
},
{
  "_id": {
    "$oid": "67523ea76f73c43ba4eb34a3"
  },
  "rescue_date": {
    "$date": "2024-07-28T03:00:00.000Z"
  },
  "case_number": "34",
  "critter_count": 1,
  "rescue_role": "Relay",
  "animal_type": "Rock Dove",
  "animal_age": "Adult",
  "conservation_status": "Least Concern",
  "original_location": "Yarmouth",
  "volunteer_notes": "Eye infection, Same trip as gull",
  "km_driven": 0,
  "user": {
    "$oid": "6755ed21907200876877bf8a"
  }
},
{
  "_id": {
    "$oid": "67523ea76f73c43ba4eb34a4"
  },
  "rescue_date": {
    "$date": "2024-07-29T03:00:00.000Z"
  },
  "case_number": "35",
  "critter_count": 4,
  "rescue_role": "Relay",
  "animal_type": "Brown Rat",
  "animal_age": "Baby",
  "conservation_status": "Least Concern",
  "original_location": "Yarmouth",
  "volunteer_notes": "Eyes not open, smidge of fur",
  "km_driven": 182,
  "user": {
    "$oid": "6755ed21907200876877bf8a"
  }
},
{
  "_id": {
    "$oid": "67523ea76f73c43ba4eb34a5"
  },
  "rescue_date": {
    "$date": "2024-07-30T03:00:00.000Z"
  },
  "case_number": "36",
  "critter_count": 1,
  "rescue_role": "Relay",
  "animal_type": "Herring Gull",
  "animal_age": "Juvenile",
  "conservation_status": "Least Concern",
  "original_location": "Yarmouth",
  "volunteer_notes": "",
  "km_driven": 182,
  "user": {
    "$oid": "6755ed21907200876877bf8a"
  }
},
{
  "_id": {
    "$oid": "67523ea76f73c43ba4eb34a6"
  },
  "rescue_date": {
    "$date": "2024-08-01T03:00:00.000Z"
  },
  "case_number": "37",
  "critter_count": 1,
  "rescue_role": "Relay",
  "animal_type": "Robin",
  "animal_age": "Baby",
  "conservation_status": "Least Concern",
  "original_location": "Yarmouth",
  "volunteer_notes": "",
  "km_driven": 182,
  "user": {
    "$oid": "6755ed21907200876877bf8a"
  }
},
{
  "_id": {
    "$oid": "67523ea76f73c43ba4eb34a7"
  },
  "rescue_date": {
    "$date": "2024-08-04T03:00:00.000Z"
  },
  "case_number": "38",
  "critter_count": 1,
  "rescue_role": "Relay",
  "animal_type": "Great black-backed gull",
  "animal_age": "Juvenile",
  "conservation_status": "Vulnerable",
  "original_location": "Barrington",
  "volunteer_notes": "",
  "km_driven": 182,
  "user": {
    "$oid": "6755ed21907200876877bf8a"
  }
},
{
  "_id": {
    "$oid": "67523ea76f73c43ba4eb34a8"
  },
  "rescue_date": {
    "$date": "2024-08-04T03:00:00.000Z"
  },
  "case_number": "39",
  "critter_count": 1,
  "rescue_role": "Relay",
  "animal_type": "Great black-backed gull",
  "animal_age": "Adult",
  "conservation_status": "Vulnerable",
  "original_location": "Barrington",
  "volunteer_notes": "Very old; porcupine quills in feet. Same trip as other gull",
  "km_driven": 0,
  "user": {
    "$oid": "6755ed21907200876877bf8a"
  }
},
{
  "_id": {
    "$oid": "67523ea76f73c43ba4eb34a9"
  },
  "rescue_date": {
    "$date": "2024-08-04T03:00:00.000Z"
  },
  "case_number": "40",
  "critter_count": 1,
  "rescue_role": "Relay",
  "animal_type": "Herring Gull",
  "animal_age": "Juvenile",
  "conservation_status": "Least Concern",
  "original_location": "Yarmouth",
  "volunteer_notes": "Same trip as other gulls",
  "km_driven": 0,
  "user": {
    "$oid": "6755ed21907200876877bf8a"
  }
},
{
  "_id": {
    "$oid": "67523ea76f73c43ba4eb34aa"
  },
  "rescue_date": {
    "$date": "2024-08-13T03:00:00.000Z"
  },
  "case_number": "41",
  "critter_count": 1,
  "rescue_role": "Pickup",
  "animal_type": "Common Grackle",
  "animal_age": "Adult",
  "conservation_status": "Least Concern",
  "original_location": "Shelburne",
  "volunteer_notes": "Caller met me at gas station",
  "km_driven": 182,
  "user": {
    "$oid": "6755ed21907200876877bf8a"
  }
},
{
  "_id": {
    "$oid": "67523ea76f73c43ba4eb34ab"
  },
  "rescue_date": {
    "$date": "2024-08-13T03:00:00.000Z"
  },
  "case_number": "42",
  "critter_count": 1,
  "rescue_role": "Relay",
  "animal_type": "Herring Gull",
  "animal_age": "Adult",
  "conservation_status": "Least Concern",
  "original_location": "Yarmouth",
  "volunteer_notes": "Same trip as grackle",
  "km_driven": 0,
  "user": {
    "$oid": "6755ed21907200876877bf8a"
  }
},
{
  "_id": {
    "$oid": "67523ea76f73c43ba4eb34ac"
  },
  "rescue_date": {
    "$date": "2024-08-13T03:00:00.000Z"
  },
  "case_number": "43",
  "critter_count": 1,
  "rescue_role": "Relay",
  "animal_type": "Cedar Waxwing",
  "animal_age": "Adult",
  "conservation_status": "Least Concern",
  "original_location": "Yarmouth",
  "volunteer_notes": "Same trip as grackle",
  "km_driven": 0,
  "user": {
    "$oid": "6755ed21907200876877bf8a"
  }
},
{
  "_id": {
    "$oid": "67523ea76f73c43ba4eb34ad"
  },
  "rescue_date": {
    "$date": "2024-08-16T03:00:00.000Z"
  },
  "case_number": "44",
  "critter_count": 1,
  "rescue_role": "Pickup",
  "animal_type": "Broadwinged Hawk",
  "animal_age": "Juvenile",
  "conservation_status": "Least Concern",
  "original_location": "Shelburne",
  "volunteer_notes": "",
  "km_driven": 182,
  "user": {
    "$oid": "6755ed21907200876877bf8a"
  }
},
{
  "_id": {
    "$oid": "67523ea76f73c43ba4eb34ae"
  },
  "rescue_date": {
    "$date": "2024-08-19T03:00:00.000Z"
  },
  "case_number": "45",
  "critter_count": 1,
  "rescue_role": "Relay",
  "animal_type": "Rock Dove",
  "animal_age": "Adult",
  "conservation_status": "Least Concern",
  "original_location": "Barrington",
  "volunteer_notes": "",
  "km_driven": 182,
  "user": {
    "$oid": "6755ed21907200876877bf8a"
  }
},
{
  "_id": {
    "$oid": "67523ea76f73c43ba4eb34af"
  },
  "rescue_date": {
    "$date": "2024-08-21T03:00:00.000Z"
  },
  "case_number": "46",
  "critter_count": 2,
  "rescue_role": "Relay",
  "animal_type": "Herring Gull",
  "animal_age": "Juvenile",
  "conservation_status": "Least Concern",
  "original_location": "Yarmouth",
  "volunteer_notes": "",
  "km_driven": 182,
  "user": {
    "$oid": "6755ed21907200876877bf8a"
  }
},
{
  "_id": {
    "$oid": "67523ea76f73c43ba4eb34b0"
  },
  "rescue_date": {
    "$date": "2024-08-23T03:00:00.000Z"
  },
  "case_number": "47",
  "critter_count": 1,
  "rescue_role": "Pickup",
  "animal_type": "Least Sandpiper",
  "animal_age": "Adult",
  "conservation_status": "Least Concern",
  "original_location": "Port Mouton",
  "volunteer_notes": "",
  "km_driven": 106,
  "user": {
    "$oid": "6755ed21907200876877bf8a"
  }
},
{
  "_id": {
    "$oid": "67524b2f8d76cd3e1c57bba6"
  },
  "case_number": "678",
  "rescue_date": {
    "$date": "2024-12-05T00:00:00.000Z"
  },
  "rescue_role": "Relay",
  "critter_count": 1,
  "animal_type": "TEST FROG",
  "animal_age": "Baby",
  "conservation_status": "Least Concern",
  "original_location": "Bridgewater",
  "km_driven": 123,
  "volunteer_notes": "",
  "__v": 0,
  "user": {
    "$oid": "6755ed21907200876877bf8a"
  }
}]